webster/__init__.py
webster/conf/__init__.py
webster/conf/settings.py
webster/core/__init__.py
webster/core/downloader.py
webster/core/parser.py
webster/crawler.py
webster/net/__init__.py
webster/net/request/__init__.py
webster/pipelines/__init__.py
webster/pipelines/db_pipeline.py
webster/robotstxt.py
webster/utils/__init__.py
webster/utils/url_tools.py
webster/utils/validators.py
webster_crawler-0.1.0.dist-info/LICENSE.md
webster_crawler-0.1.0.dist-info/WHEEL
webster_crawler-0.1.0.dist-info/METADATA
webster_crawler-0.1.0.dist-info/RECORD
