Metadata-Version: 2.1
Name: webster-crawler
Version: 0.1.0
Summary: Website crawler-ish thing?
Home-page: https://github.com/HRemonen/Webster
License: BSD-3-Clause
Author: Henri Remonen
Author-email: henri@remonen.fi
Maintainer: Henri Remonen
Maintainer-email: henri@remonen.fi
Requires-Python: >=3.10,<4.0
Classifier: License :: OSI Approved :: BSD License
Classifier: Programming Language :: Python :: 3
Classifier: Programming Language :: Python :: 3.10
Requires-Dist: lxml (>=4.9.1,<5.0.0)
Requires-Dist: pycurl (>=7.45.1,<8.0.0)
Requires-Dist: pymongo (>=4.2.0,<5.0.0)
Requires-Dist: w3lib (>=2.0.1,<3.0.0)
Project-URL: Bug Tracker, https://github.com/HRemonen/Webster/issues
Project-URL: Repository, https://github.com/HRemonen/Webster
